mlpipe/__init__.py
mlpipe/callbacks/__init__.py
mlpipe/callbacks/fill_training.py
mlpipe/callbacks/save_to_mongodb.py
mlpipe/callbacks/update_manager.py
mlpipe/data_reader/__init__.py
mlpipe/data_reader/base_data_generator.py
mlpipe/data_reader/i_cache.py
mlpipe/data_reader/redis_cache.py
mlpipe/data_reader/mongodb/__init__.py
mlpipe/data_reader/mongodb/data_loader.py
mlpipe/data_reader/mongodb/mongodb_connect.py
mlpipe/data_reader/mongodb/mongodb_generator.py
mlpipe/processors/__init__.py
mlpipe/processors/i_processor.py
mlpipe/schemas/__init__.py
mlpipe/schemas/result.py
mlpipe/schemas/training.py
mlpipe/scripts/__init__.py
mlpipe/scripts/setup_config.py
mlpipe/utils/__init__.py
mlpipe/utils/api_endpoints.py
mlpipe/utils/config.py
mlpipe/utils/logger.py
mlpipe_trainer-0.5.1.dist-info/LICENSE
mlpipe_trainer-0.5.1.dist-info/METADATA
mlpipe_trainer-0.5.1.dist-info/WHEEL
mlpipe_trainer-0.5.1.dist-info/top_level.txt
mlpipe_trainer-0.5.1.dist-info/RECORD
