Metadata-Version: 2.1
Name: mlpipe-trainer
Version: 0.5.1
Summary: Manage training results, weights and data flow of your Tensorflow models
Home-page: https://github.com/j-o-d-o/MLPipe-Trainer
Author: Johannes Dobler
Author-email: jdobler@protonmail.com
License: UNKNOWN
Platform: UNKNOWN
Classifier: Programming Language :: Python :: 3
Classifier: Programming Language :: Python :: 3.6
Classifier: License :: OSI Approved :: MIT License
Classifier: Intended Audience :: Developers
Classifier: Intended Audience :: Education
Classifier: Intended Audience :: Science/Research
Requires-Dist: numpy (>=1.16.0)
Requires-Dist: pymongo (>=3.7.0)
Requires-Dist: h5py (>=2.9.0)
Requires-Dist: requests (>=2.21.0)
Requires-Dist: namedlist (>=1.7)
Requires-Dist: tensorflow (>=1.14.0)
